spot2mp3_gooosexe/.cache
spot2mp3_gooosexe/Pipfile
spot2mp3_gooosexe/Pipfile.lock
spot2mp3_gooosexe/__init__.py
spot2mp3_gooosexe/log.txt
spot2mp3_gooosexe/main.py
spot2mp3_gooosexe-1.0.0.dist-info/METADATA
spot2mp3_gooosexe-1.0.0.dist-info/WHEEL
spot2mp3_gooosexe-1.0.0.dist-info/licenses/LICENSE
spot2mp3_gooosexe-1.0.0.dist-info/RECORD
