Metadata-Version: 2.3
Name: spot2mp3_gooosexe
Version: 1.0.0
Summary: A simple tool to convert Spotify playlists to mp3 files.
Project-URL: Homepage, https://github.com/gooosexe/spot2mp3
Project-URL: Issues, https://github.com/gooosexe/spot2mp3/issues
Author-email: Oliver Huang <ohuang4131@gmail.com>
License-File: LICENSE
Classifier: License :: OSI Approved :: MIT License
Classifier: Operating System :: OS Independent
Classifier: Programming Language :: Python :: 3
Requires-Python: >=3.8
